monollm/__init__.py
monollm/__main__.py
monollm/cli.py
monollm/cli/MACHINE-QUICK-REFERENCE.md
monollm/cli/README-MACHINE.md
monollm/cli/README.md
monollm/cli/__init__.py
monollm/cli/config_manager.py
monollm/cli/machine_interface.py
monollm/cli/main.py
monollm/cli/output_formatter.py
monollm/cli/user_interface.py
monollm/config/__init__.py
monollm/config/loader.py
monollm/config/manager.py
monollm/core/client.py
monollm/core/exceptions.py
monollm/core/models.py
monollm/providers/__init__.py
monollm/providers/anthropic_provider.py
monollm/providers/base.py
monollm/providers/deepseek_provider.py
monollm/providers/google_provider.py
monollm/providers/openai_provider.py
monollm/providers/qwen_provider.py
monollm/providers/volcengine_provider.py
monollm-0.1.3.dist-info/METADATA
monollm-0.1.3.dist-info/WHEEL
monollm-0.1.3.dist-info/entry_points.txt
monollm-0.1.3.dist-info/licenses/LICENSE
monollm-0.1.3.dist-info/RECORD
