Metadata-Version: 2.4
Name: monollm
Version: 0.1.3
Summary: A unified framework for accessing multiple LLM providers with comprehensive CLI and machine interface
Project-URL: Homepage, https://github.com/cyborgoat/monollm
Project-URL: Documentation, https://cyborgoat.github.io/monollm/
Project-URL: Repository, https://github.com/cyborgoat/monollm.git
Project-URL: Issues, https://github.com/cyborgoat/monollm/issues
Project-URL: Changelog, https://github.com/cyborgoat/monollm/blob/main/CHANGELOG.md
Author-email: cyborgoat <cyborgoat@outlook.com>
Maintainer-email: cyborgoat <cyborgoat@outlook.com>
License-Expression: MIT
License-File: LICENSE
Keywords: ai,anthropic,api,async,claude,deepseek,gpt,llm,openai,qwen,streaming,unified
Classifier: Development Status :: 4 - Beta
Classifier: Intended Audience :: Developers
Classifier: License :: OSI Approved :: MIT License
Classifier: Operating System :: OS Independent
Classifier: Programming Language :: Python :: 3
Classifier: Programming Language :: Python :: 3 :: Only
Classifier: Programming Language :: Python :: 3.12
Classifier: Topic :: Internet :: WWW/HTTP :: Dynamic Content
Classifier: Topic :: Scientific/Engineering :: Artificial Intelligence
Classifier: Topic :: Software Development :: Libraries :: Python Modules
Classifier: Typing :: Typed
Requires-Python: >=3.12
Requires-Dist: anthropic>=0.25.0
Requires-Dist: httpx>=0.25.0
Requires-Dist: openai>=1.0.0
Requires-Dist: pydantic>=2.0.0
Requires-Dist: python-dotenv>=1.0.0
Requires-Dist: rich>=13.0.0
Requires-Dist: tenacity>=8.0.0
Requires-Dist: typer>=0.9.0
Provides-Extra: dev
Requires-Dist: mypy>=1.5.0; extra == 'dev'
Requires-Dist: pre-commit>=3.0.0; extra == 'dev'
Requires-Dist: pytest-asyncio>=0.21.0; extra == 'dev'
Requires-Dist: pytest-cov>=4.0.0; extra == 'dev'
Requires-Dist: pytest>=7.0.0; extra == 'dev'
Requires-Dist: ruff>=0.1.0; extra == 'dev'
Requires-Dist: types-requests>=2.31.0; extra == 'dev'
Provides-Extra: docs
Requires-Dist: linkify-it-py>=2.0.0; extra == 'docs'
Requires-Dist: mdit-py-plugins>=0.4.0; extra == 'docs'
Requires-Dist: myst-parser>=2.0.0; extra == 'docs'
Requires-Dist: sphinx-autobuild>=2021.3.14; extra == 'docs'
Requires-Dist: sphinx-autodoc-typehints>=1.24.0; extra == 'docs'
Requires-Dist: sphinx-rtd-theme>=1.3.0; extra == 'docs'
Requires-Dist: sphinx>=7.0.0; extra == 'docs'
Provides-Extra: test
Requires-Dist: httpx>=0.25.0; extra == 'test'
Requires-Dist: pytest-asyncio>=0.21.0; extra == 'test'
Requires-Dist: pytest-cov>=4.0.0; extra == 'test'
Requires-Dist: pytest>=7.0.0; extra == 'test'
